theine/__init__.py
theine/exceptions.py
theine/models.py
theine/py.typed
theine/striped_buffer.py
theine/theine.py
theine/utils.py
theine/write_buffer.py
theine/adapters/__init__.py
theine/adapters/django.py
theine-2.0.0.dist-info/METADATA
theine-2.0.0.dist-info/WHEEL
theine-2.0.0.dist-info/licenses/LICENSE
theine-2.0.0.dist-info/RECORD
