Metadata-Version: 2.4
Name: theine
Version: 2.0.0
Summary: high performance in-memory cache
Author-email: Yiling-J <njjyl723@gmail.com>
License-Expression: BSD-3-Clause
License-File: LICENSE
Classifier: Programming Language :: Python :: 3
Classifier: Topic :: Software Development :: Libraries
Classifier: Topic :: Software Development :: Libraries :: Python Modules
Requires-Python: <4.0,>=3.9
Requires-Dist: theine-core<3,>=2.0.0
Requires-Dist: typing-extensions<5,>=4.4.0
Requires-Dist: zstandard>=0.24.0.dev0
